COPYING
MANIFEST.in
README.rst
bootstrap.py
buildout.cfg
setup.py
feret_annotations/00050fa001d_931230.pos
feret_annotations/00051fa001d_931230.pos
feret_annotations/00055fa001d_931230.pos
feret_annotations/00062fa001d_931230.pos
feret_annotations/00063fa001d_931230.pos
feret_annotations/00064fa001d_931230.pos
feret_annotations/00069fa001d_931230.pos
feret_annotations/00070fa001d_931230.pos
feret_annotations/00073fa001d_931230.pos
feret_annotations/00074fa001d_931230.pos
feret_annotations/00075fa001d_931230.pos
feret_annotations/00076fa001d_931230.pos
feret_annotations/00077fa001d_931230.pos
feret_annotations/00078fa001d_931230.pos
feret_annotations/00080fa001d_931230.pos
feret_annotations/00082fa011d_931230.pos
feret_annotations/00089fa011d_931230.pos
feret_annotations/00091fa011d_931230.pos
feret_annotations/00093fa011d_931230.pos
feret_annotations/00097fa011d_931230.pos
feret_annotations/00104fa011d_931230.pos
feret_annotations/00107fa011d_931230.pos
feret_annotations/00115fa011d_931230.pos
feret_annotations/00132fa011d_931230.pos
feret_annotations/00140fa011d_931230.pos
feret_annotations/00142fa011d_931230.pos
feret_annotations/00144fa011d_931230.pos
feret_annotations/00146fa011d_931230.pos
feret_annotations/00149fa001_931230.pos
feret_annotations/00150fa011d_931230.pos
feret_annotations/00153fa001d_931230.pos
feret_annotations/00160fa001d_931230.pos
feret_annotations/00161fa001d_931230.pos
feret_annotations/00162fa001d_931230.pos
feret_annotations/00165fa001d_931230.pos
feret_annotations/00170fa001d_931230.pos
feret_annotations/00171fa001d_931230.pos
feret_annotations/00172fa001d_931230.pos
feret_annotations/00175fa001d_931230.pos
feret_annotations/00180fa001d_931230.pos
feret_annotations/00181fa001d_931230.pos
feret_annotations/00183fa010_940128.pos
feret_annotations/00184fa010_940128.pos
feret_annotations/00188fa010_940128.pos
feret_annotations/00189fa010_940128.pos
feret_annotations/00193fa000_940128.pos
feret_annotations/00194fa000_940128.pos
xbob.gender.bimodal.egg-info/PKG-INFO
xbob.gender.bimodal.egg-info/SOURCES.txt
xbob.gender.bimodal.egg-info/dependency_links.txt
xbob.gender.bimodal.egg-info/entry_points.txt
xbob.gender.bimodal.egg-info/namespace_packages.txt
xbob.gender.bimodal.egg-info/requires.txt
xbob.gender.bimodal.egg-info/top_level.txt
