Metadata-Version: 1.1
Name: xbob.gender.bimodal
Version: 0.0.1a0
Summary: Bimodal gender recognition
Home-page: http://pypi.python.org/pypi/xbob.gender.bimodal
Author: Laurent El Shafey
Author-email: laurent.el-shafey@idiap.ch
License: GPLv3
Keywords: bob,xbob,gender recognition,face,speech,bimodal
Platform: UNKNOWN
Classifier: Development Status :: 3 - Alpha
Classifier: Intended Audience :: Developers
Classifier: License :: OSI Approved :: GNU General Public License v3 (GPLv3)
Classifier: Natural Language :: English
Classifier: Programming Language :: Python
Classifier: Topic :: Scientific/Engineering :: Artificial Intelligence
